assets/allele_calling.png
assets/benchmark.ipynb
assets/blast_id_dist.py
assets/mash_blast_correlation.ipynb
assets/mash_blast_correlation.py
assets/requirements_assets.txt
assets/taranis_schema.png
docs/requirements.txt
taranys/__init__.py
taranys/__main__.py
taranys/allele_calling.py
taranys/analyze_schema.py
taranys/blast.py
taranys/clustering.py
taranys/distance.py
taranys/eval_cluster.py
taranys/inferred_alleles.py
taranys/reference_alleles.py
taranys/seq_cluster.py
taranys/utils.py
test/__init__.py
test/MLST_listeria/analyze_schema/lm0002.fasta
test/MLST_listeria/analyze_schema/lmo0011.fasta
test/MLST_listeria/analyze_schema/lmo0019.fasta
test/MLST_listeria/reference_allele/lmo1762.fasta
test/MLST_listeria/reference_allele/lmo1784.fasta
test/profile_MLST_listeria/profiles_csv.csv
test/reference_alleles_mlst_listeria/abcZ.fasta
test/reference_alleles_mlst_listeria/bglA.fasta
test/reference_alleles_mlst_listeria/cat.fasta
test/reference_alleles_mlst_listeria/dapE.fasta
test/reference_alleles_mlst_listeria/dat.fasta
test/reference_alleles_mlst_listeria/ldh.fasta
test/reference_alleles_mlst_listeria/lhkA.fasta
test/reference_listeria/GCF_002213505.1_ASM221350v1_genomic.fna
test/samples_listeria/4122_S1_paired_assembly.fasta
test/samples_listeria/4123_S2_paired_assembly.fasta
taranys-3.0.1.dist-info/LICENSE
taranys-3.0.1.dist-info/METADATA
taranys-3.0.1.dist-info/WHEEL
taranys-3.0.1.dist-info/entry_points.txt
taranys-3.0.1.dist-info/top_level.txt
taranys-3.0.1.dist-info/RECORD
