Metadata-Version: 2.1
Name: taranys
Version: 3.0.1
Summary: cg/wgMLST allele calling software, schema evaluation and allele distance estimation for outbreak reserch.
Author-email: Sara Monzon <smonzon@isciii.es>, Luis Chapado <lchapado@externos.isciii.es>
Maintainer-email: Sara Monzon <smonzon@isciii.es>, Luis Chapado <lchapado@externos.isciii.es>
License:                     GNU GENERAL PUBLIC LICENSE
Project-URL: Homepage, https://github.com/bu-isciii/taranys
Project-URL: Issues, https://github.com/bu-isciii/taranys/issues
Keywords: bioinformatics,assembly,cgMLST,wgMLST,MLST schema
Requires-Python: >=3.10
License-File: LICENSE
Requires-Dist: igraph>=0.9.8
Requires-Dist: rich>=13.4.1
Requires-Dist: click>=8.1.3
Requires-Dist: leidenalg>=0.9.1
Requires-Dist: questionary>=1.10.0
Requires-Dist: bio>=1.6.0
Requires-Dist: scikit-learn>=1.2.0
Requires-Dist: plotly>=5.11.0
Requires-Dist: kaleido>=0.2.1
Requires-Dist: six>=1.16.0
